sparse_deferred/__init__.py
sparse_deferred/algorithms/__init__.py
sparse_deferred/algorithms/auto_hop.py
sparse_deferred/algorithms/auto_hop_test.py
sparse_deferred/algorithms/svd.py
sparse_deferred/algorithms/svd_test.py
sparse_deferred/algorithms/topological_sort.py
sparse_deferred/algorithms/topological_sort_test.py
sparse_deferred/algorithms/traversal.py
sparse_deferred/algorithms/traversal_test.py
sparse_deferred/algorithms/virtualize.py
sparse_deferred/algorithms/virtualize_test.py
sparse_deferred/examples/cora_jax.py
sparse_deferred/examples/data.py
sparse_deferred/examples/malnet_gnn.py
sparse_deferred/examples/malnet_nn.py
sparse_deferred/examples/models.py
sparse_deferred/gnn/__init__.py
sparse_deferred/gnn/heterogeneous_gnn.py
sparse_deferred/gnn/heterogeneous_gnn_test.py
sparse_deferred/implicit/matrix.py
sparse_deferred/implicit/matrix_test.py
sparse_deferred/jax/__init__.py
sparse_deferred/jax/jax_test.py
sparse_deferred/nn/edges.py
sparse_deferred/nn/edges_test.py
sparse_deferred/np/__init__.py
sparse_deferred/np/np_test.py
sparse_deferred/structs/graph_struct.py
sparse_deferred/structs/graph_struct_test.py
sparse_deferred/tf/__init__.py
sparse_deferred/tf/graph.py
sparse_deferred/tf/tf_engine.py
sparse_deferred/tf/tf_engine_test.py
sparse_deferred/tf/tf_matrix.py
sparse_deferred/tfgnn/__init__.py
sparse_deferred/tfgnn/io.py
sparse_deferred/tfgnn/io_test.py
sparse_deferred-1.0.0.dist-info/METADATA
sparse_deferred-1.0.0.dist-info/WHEEL
sparse_deferred-1.0.0.dist-info/top_level.txt
sparse_deferred-1.0.0.dist-info/RECORD
