Metadata-Version: 2.4
Name: sparse_deferred
Version: 1.0.0
Summary: Linear algebra library for sparse and deferred operations.
Author-email: Sami Abu-El-Haija <haija@google.com>, Michael Galkin <mgalkin@google.com>, Brandom Mayer <bmayer@google.com>, Mathieu Guillame-Bert <gbm@google.com>, Bryan Perozzi <bperozzi@google.com>, Hasan Awais <hasanawais@google.com>, Aditya Mishra <mishraaditya@google.com>
Project-URL: Homepage, https://github.com/google-research/google-research/tree/master/sparse_deferred
Classifier: Programming Language :: Python :: 3
Requires-Python: >=3.10
